{
  "popeReports": {
    "16": [
      3,
      5
    ],
    "24": [
      4,
      6
    ],
    "8": [
      2,
      4
    ]
  },
  "faithTrackPoints": {
    "9": 4,
    "12": 6,
    "15": 9,
    "18": 12,
    "3": 1,
    "21": 16,
    "6": 2,
    "24": 20
  },
  "baseProductionPower": {
    "input": [
      null,
      null
    ],
    "output": [
      null
    ]
  },
  "leaderCards": [
    {
      "cardRequirements": {
        "resourceRequirements": {},
        "cardColorRequirements": {
          "GREEN": 1,
          "YELLOW": 1
        },
        "cardLevelRequirements": {}
      },
      "specialAbility": {
        "type": "DISCOUNT",
        "targetResource": "SERVANT"
      },
      "victoryPoints": 2
    },
    {
      "cardRequirements": {
        "resourceRequirements": {},
        "cardColorRequirements": {
          "PURPLE": 1,
          "BLUE": 1
        },
        "cardLevelRequirements": {}
      },
      "specialAbility": {
        "type": "DISCOUNT",
        "targetResource": "SHIELD"
      },
      "victoryPoints": 2
    },
    {
      "cardRequirements": {
        "resourceRequirements": {},
        "cardColorRequirements": {
          "GREEN": 1,
          "BLUE": 1
        },
        "cardLevelRequirements": {}
      },
      "specialAbility": {
        "type": "DISCOUNT",
        "targetResource": "STONE"
      },
      "victoryPoints": 2
    },
    {
      "cardRequirements": {
        "resourceRequirements": {},
        "cardColorRequirements": {
          "PURPLE": 1,
          "YELLOW": 1
        },
        "cardLevelRequirements": {}
      },
      "specialAbility": {
        "type": "DISCOUNT",
        "targetResource": "COIN"
      },
      "victoryPoints": 2
    },
    {
      "cardRequirements": {
        "resourceRequirements": {
          "COIN": 5
        },
        "cardColorRequirements": {},
        "cardLevelRequirements": {}
      },
      "specialAbility": {
        "type": "DEPOT",
        "targetResource": "STONE"
      },
      "victoryPoints": 3
    },
    {
      "cardRequirements": {
        "resourceRequirements": {
          "STONE": 5
        },
        "cardColorRequirements": {},
        "cardLevelRequirements": {}
      },
      "specialAbility": {
        "type": "DEPOT",
        "targetResource": "SERVANT"
      },
      "victoryPoints": 3
    },
    {
      "cardRequirements": {
        "resourceRequirements": {
          "SERVANT": 5
        },
        "cardColorRequirements": {},
        "cardLevelRequirements": {}
      },
      "specialAbility": {
        "type": "DEPOT",
        "targetResource": "SHIELD"
      },
      "victoryPoints": 3
    },
    {
      "cardRequirements": {
        "resourceRequirements": {
          "SHIELD": 5
        },
        "cardColorRequirements": {},
        "cardLevelRequirements": {}
      },
      "specialAbility": {
        "type": "DEPOT",
        "targetResource": "COIN"
      },
      "victoryPoints": 3
    },
    {
      "cardRequirements": {
        "resourceRequirements": {},
        "cardColorRequirements": {
          "BLUE": 1,
          "YELLOW": 2
        },
        "cardLevelRequirements": {}
      },
      "specialAbility": {
        "type": "EXCHANGE",
        "targetResource": "SERVANT"
      },
      "victoryPoints": 5
    },
    {
      "cardRequirements": {
        "resourceRequirements": {},
        "cardColorRequirements": {
          "PURPLE": 1,
          "GREEN": 2
        },
        "cardLevelRequirements": {}
      },
      "specialAbility": {
        "type": "EXCHANGE",
        "targetResource": "SHIELD"
      },
      "victoryPoints": 5
    },
    {
      "cardRequirements": {
        "resourceRequirements": {},
        "cardColorRequirements": {
          "BLUE": 2,
          "YELLOW": 1
        },
        "cardLevelRequirements": {}
      },
      "specialAbility": {
        "type": "EXCHANGE",
        "targetResource": "STONE"
      },
      "victoryPoints": 5
    },
    {
      "cardRequirements": {
        "resourceRequirements": {},
        "cardColorRequirements": {
          "PURPLE": 2,
          "GREEN": 1
        },
        "cardLevelRequirements": {}
      },
      "specialAbility": {
        "type": "EXCHANGE",
        "targetResource": "COIN"
      },
      "victoryPoints": 5
    },
    {
      "cardRequirements": {
        "resourceRequirements": {},
        "cardColorRequirements": {},
        "cardLevelRequirements": {
          "YELLOW": 2
        }
      },
      "specialAbility": {
        "type": "PRODUCTION",
        "targetResource": "SHIELD"
      },
      "victoryPoints": 4
    },
    {
      "cardRequirements": {
        "resourceRequirements": {},
        "cardColorRequirements": {},
        "cardLevelRequirements": {
          "BLUE": 2
        }
      },
      "specialAbility": {
        "type": "PRODUCTION",
        "targetResource": "SERVANT"
      },
      "victoryPoints": 4
    },
    {
      "cardRequirements": {
        "resourceRequirements": {},
        "cardColorRequirements": {},
        "cardLevelRequirements": {
          "PURPLE": 2
        }
      },
      "specialAbility": {
        "type": "PRODUCTION",
        "targetResource": "STONE"
      },
      "victoryPoints": 4
    },
    {
      "cardRequirements": {
        "resourceRequirements": {},
        "cardColorRequirements": {},
        "cardLevelRequirements": {
          "GREEN": 2
        }
      },
      "specialAbility": {
        "type": "PRODUCTION",
        "targetResource": "COIN"
      },
      "victoryPoints": 4
    }
  ],
  "developmentCards": [
    {
      "PURPLE": [
        {
          "cost": {
            "SERVANT": 2
          },
          "level": 1,
          "productionInput": {
            "STONE": 1
          },
          "productionOutput": {
            "FAITH": 1
          },
          "color": "PURPLE",
          "victoryPoints": 1
        },
        {
          "cost": {
            "SERVANT": 1,
            "COIN": 1,
            "SHIELD": 1
          },
          "level": 1,
          "productionInput": {
            "COIN": 1
          },
          "productionOutput": {
            "SHIELD": 1
          },
          "color": "PURPLE",
          "victoryPoints": 2
        },
        {
          "cost": {
            "SERVANT": 3
          },
          "level": 1,
          "productionInput": {
            "COIN": 2
          },
          "productionOutput": {
            "SERVANT": 1,
            "STONE": 1,
            "SHIELD": 1
          },
          "color": "PURPLE",
          "victoryPoints": 3
        },
        {
          "cost": {
            "SERVANT": 2,
            "STONE": 2
          },
          "level": 1,
          "productionInput": {
            "COIN": 1,
            "SHIELD": 1
          },
          "productionOutput": {
            "STONE": 2,
            "FAITH": 1
          },
          "color": "PURPLE",
          "victoryPoints": 4
        }
      ],
      "GREEN": [
        {
          "cost": {
            "SHIELD": 2
          },
          "level": 1,
          "productionInput": {
            "COIN": 1
          },
          "productionOutput": {
            "FAITH": 1
          },
          "color": "GREEN",
          "victoryPoints": 1
        },
        {
          "cost": {
            "SERVANT": 1,
            "STONE": 1,
            "SHIELD": 1
          },
          "level": 1,
          "productionInput": {
            "STONE": 1
          },
          "productionOutput": {
            "SERVANT": 1
          },
          "color": "GREEN",
          "victoryPoints": 2
        },
        {
          "cost": {
            "SHIELD": 3
          },
          "level": 1,
          "productionInput": {
            "SERVANT": 2
          },
          "productionOutput": {
            "STONE": 1,
            "COIN": 1,
            "SHIELD": 1
          },
          "color": "GREEN",
          "victoryPoints": 3
        },
        {
          "cost": {
            "COIN": 2,
            "SHIELD": 2
          },
          "level": 1,
          "productionInput": {
            "SERVANT": 1,
            "STONE": 1
          },
          "productionOutput": {
            "COIN": 2,
            "FAITH": 1
          },
          "color": "GREEN",
          "victoryPoints": 4
        }
      ],
      "BLUE": [
        {
          "cost": {
            "COIN": 2
          },
          "level": 1,
          "productionInput": {
            "SHIELD": 1
          },
          "productionOutput": {
            "FAITH": 1
          },
          "color": "BLUE",
          "victoryPoints": 1
        },
        {
          "cost": {
            "SERVANT": 1,
            "STONE": 1,
            "COIN": 1
          },
          "level": 1,
          "productionInput": {
            "SERVANT": 1
          },
          "productionOutput": {
            "STONE": 1
          },
          "color": "BLUE",
          "victoryPoints": 2
        },
        {
          "cost": {
            "COIN": 3
          },
          "level": 1,
          "productionInput": {
            "STONE": 2
          },
          "productionOutput": {
            "SERVANT": 1,
            "COIN": 1,
            "SHIELD": 1
          },
          "color": "BLUE",
          "victoryPoints": 3
        },
        {
          "cost": {
            "SERVANT": 2,
            "COIN": 2
          },
          "level": 1,
          "productionInput": {
            "STONE": 1,
            "SHIELD": 1
          },
          "productionOutput": {
            "SERVANT": 2,
            "FAITH": 1
          },
          "color": "BLUE",
          "victoryPoints": 4
        }
      ],
      "YELLOW": [
        {
          "cost": {
            "STONE": 2
          },
          "level": 1,
          "productionInput": {
            "SERVANT": 1
          },
          "productionOutput": {
            "FAITH": 1
          },
          "color": "YELLOW",
          "victoryPoints": 1
        },
        {
          "cost": {
            "STONE": 1,
            "COIN": 1,
            "SHIELD": 1
          },
          "level": 1,
          "productionInput": {
            "SHIELD": 1
          },
          "productionOutput": {
            "COIN": 1
          },
          "color": "YELLOW",
          "victoryPoints": 2
        },
        {
          "cost": {
            "STONE": 3
          },
          "level": 1,
          "productionInput": {
            "SHIELD": 2
          },
          "productionOutput": {
            "SERVANT": 1,
            "STONE": 1,
            "COIN": 1
          },
          "color": "YELLOW",
          "victoryPoints": 3
        },
        {
          "cost": {
            "STONE": 2,
            "SHIELD": 2
          },
          "level": 1,
          "productionInput": {
            "SERVANT": 1,
            "COIN": 1
          },
          "productionOutput": {
            "SHIELD": 2,
            "FAITH": 1
          },
          "color": "YELLOW",
          "victoryPoints": 4
        }
      ]
    },
    {
      "PURPLE": [
        {
          "cost": {
            "SERVANT": 4
          },
          "level": 2,
          "productionInput": {
            "COIN": 1
          },
          "productionOutput": {
            "FAITH": 2
          },
          "color": "PURPLE",
          "victoryPoints": 5
        },
        {
          "cost": {
            "SERVANT": 3,
            "COIN": 2
          },
          "level": 2,
          "productionInput": {
            "SERVANT": 1,
            "COIN": 1
          },
          "productionOutput": {
            "SHIELD": 3
          },
          "color": "PURPLE",
          "victoryPoints": 6
        },
        {
          "cost": {
            "SERVANT": 5
          },
          "level": 2,
          "productionInput": {
            "STONE": 2
          },
          "productionOutput": {
            "COIN": 2,
            "FAITH": 2
          },
          "color": "PURPLE",
          "victoryPoints": 7
        },
        {
          "cost": {
            "SERVANT": 3,
            "SHIELD": 3
          },
          "level": 2,
          "productionInput": {
            "STONE": 1
          },
          "productionOutput": {
            "SERVANT": 2,
            "FAITH": 1
          },
          "color": "PURPLE",
          "victoryPoints": 8
        }
      ],
      "GREEN": [
        {
          "cost": {
            "SHIELD": 4
          },
          "level": 2,
          "productionInput": {
            "STONE": 1
          },
          "productionOutput": {
            "FAITH": 2
          },
          "color": "GREEN",
          "victoryPoints": 5
        },
        {
          "cost": {
            "SERVANT": 2,
            "SHIELD": 3
          },
          "level": 2,
          "productionInput": {
            "SERVANT": 1,
            "SHIELD": 1
          },
          "productionOutput": {
            "STONE": 3
          },
          "color": "GREEN",
          "victoryPoints": 6
        },
        {
          "cost": {
            "SHIELD": 5
          },
          "level": 2,
          "productionInput": {
            "COIN": 2
          },
          "productionOutput": {
            "STONE": 2,
            "FAITH": 2
          },
          "color": "GREEN",
          "victoryPoints": 7
        },
        {
          "cost": {
            "COIN": 3,
            "SHIELD": 3
          },
          "level": 2,
          "productionInput": {
            "COIN": 1
          },
          "productionOutput": {
            "SHIELD": 2,
            "FAITH": 1
          },
          "color": "GREEN",
          "victoryPoints": 8
        }
      ],
      "BLUE": [
        {
          "cost": {
            "COIN": 4
          },
          "level": 2,
          "productionInput": {
            "SHIELD": 1
          },
          "productionOutput": {
            "FAITH": 2
          },
          "color": "BLUE",
          "victoryPoints": 5
        },
        {
          "cost": {
            "STONE": 2,
            "COIN": 3
          },
          "level": 2,
          "productionInput": {
            "STONE": 1,
            "COIN": 1
          },
          "productionOutput": {
            "SERVANT": 3
          },
          "color": "BLUE",
          "victoryPoints": 6
        },
        {
          "cost": {
            "COIN": 5
          },
          "level": 2,
          "productionInput": {
            "SERVANT": 2
          },
          "productionOutput": {
            "SHIELD": 2,
            "FAITH": 2
          },
          "color": "BLUE",
          "victoryPoints": 7
        },
        {
          "cost": {
            "STONE": 3,
            "COIN": 3
          },
          "level": 2,
          "productionInput": {
            "SERVANT": 1
          },
          "productionOutput": {
            "STONE": 2,
            "FAITH": 1
          },
          "color": "BLUE",
          "victoryPoints": 8
        }
      ],
      "YELLOW": [
        {
          "cost": {
            "STONE": 4
          },
          "level": 2,
          "productionInput": {
            "SHIELD": 1
          },
          "productionOutput": {
            "FAITH": 2
          },
          "color": "YELLOW",
          "victoryPoints": 5
        },
        {
          "cost": {
            "STONE": 3,
            "SHIELD": 2
          },
          "level": 2,
          "productionInput": {
            "STONE": 1,
            "SHIELD": 1
          },
          "productionOutput": {
            "COIN": 3
          },
          "color": "YELLOW",
          "victoryPoints": 6
        },
        {
          "cost": {
            "STONE": 5
          },
          "level": 2,
          "productionInput": {
            "SHIELD": 2
          },
          "productionOutput": {
            "SERVANT": 2,
            "FAITH": 2
          },
          "color": "YELLOW",
          "victoryPoints": 7
        },
        {
          "cost": {
            "SERVANT": 3,
            "STONE": 3
          },
          "level": 2,
          "productionInput": {
            "SHIELD": 1
          },
          "productionOutput": {
            "COIN": 2,
            "FAITH": 1
          },
          "color": "YELLOW",
          "victoryPoints": 8
        }
      ]
    },
    {
      "PURPLE": [
        {
          "cost": {
            "SERVANT": 6
          },
          "level": 3,
          "productionInput": {
            "STONE": 2
          },
          "productionOutput": {
            "COIN": 3,
            "FAITH": 2
          },
          "color": "PURPLE",
          "victoryPoints": 9
        },
        {
          "cost": {
            "SERVANT": 5,
            "COIN": 2
          },
          "level": 3,
          "productionInput": {
            "STONE": 1,
            "SHIELD": 1
          },
          "productionOutput": {
            "SERVANT": 2,
            "COIN": 2,
            "FAITH": 1
          },
          "color": "PURPLE",
          "victoryPoints": 10
        },
        {
          "cost": {
            "SERVANT": 7
          },
          "level": 3,
          "productionInput": {
            "COIN": 1
          },
          "productionOutput": {
            "STONE": 1,
            "FAITH": 3
          },
          "color": "PURPLE",
          "victoryPoints": 11
        },
        {
          "cost": {
            "SERVANT": 4,
            "SHIELD": 4
          },
          "level": 3,
          "productionInput": {
            "COIN": 1
          },
          "productionOutput": {
            "SERVANT": 1,
            "STONE": 3
          },
          "color": "PURPLE",
          "victoryPoints": 12
        }
      ],
      "GREEN": [
        {
          "cost": {
            "SHIELD": 6
          },
          "level": 3,
          "productionInput": {
            "COIN": 2
          },
          "productionOutput": {
            "STONE": 3,
            "FAITH": 2
          },
          "color": "GREEN",
          "victoryPoints": 9
        },
        {
          "cost": {
            "SERVANT": 2,
            "SHIELD": 5
          },
          "level": 3,
          "productionInput": {
            "SERVANT": 1,
            "COIN": 1
          },
          "productionOutput": {
            "STONE": 2,
            "SHIELD": 2,
            "FAITH": 1
          },
          "color": "GREEN",
          "victoryPoints": 10
        },
        {
          "cost": {
            "SHIELD": 7
          },
          "level": 3,
          "productionInput": {
            "SERVANT": 1
          },
          "productionOutput": {
            "COIN": 1,
            "FAITH": 3
          },
          "color": "GREEN",
          "victoryPoints": 11
        },
        {
          "cost": {
            "COIN": 4,
            "SHIELD": 4
          },
          "level": 3,
          "productionInput": {
            "STONE": 1
          },
          "productionOutput": {
            "COIN": 3,
            "SHIELD": 1
          },
          "color": "GREEN",
          "victoryPoints": 12
        }
      ],
      "BLUE": [
        {
          "cost": {
            "COIN": 6
          },
          "level": 3,
          "productionInput": {
            "SERVANT": 2
          },
          "productionOutput": {
            "SHIELD": 3,
            "FAITH": 2
          },
          "color": "BLUE",
          "victoryPoints": 9
        },
        {
          "cost": {
            "STONE": 2,
            "COIN": 5
          },
          "level": 3,
          "productionInput": {
            "COIN": 1,
            "SHIELD": 1
          },
          "productionOutput": {
            "SERVANT": 2,
            "STONE": 2,
            "FAITH": 1
          },
          "color": "BLUE",
          "victoryPoints": 10
        },
        {
          "cost": {
            "COIN": 7
          },
          "level": 3,
          "productionInput": {
            "STONE": 1
          },
          "productionOutput": {
            "SHIELD": 1,
            "FAITH": 3
          },
          "color": "BLUE",
          "victoryPoints": 11
        },
        {
          "cost": {
            "STONE": 4,
            "COIN": 4
          },
          "level": 3,
          "productionInput": {
            "SERVANT": 1
          },
          "productionOutput": {
            "COIN": 1,
            "SHIELD": 3
          },
          "color": "BLUE",
          "victoryPoints": 12
        }
      ],
      "YELLOW": [
        {
          "cost": {
            "STONE": 6
          },
          "level": 3,
          "productionInput": {
            "SHIELD": 2
          },
          "productionOutput": {
            "SERVANT": 3,
            "FAITH": 2
          },
          "color": "YELLOW",
          "victoryPoints": 9
        },
        {
          "cost": {
            "SERVANT": 2,
            "STONE": 5
          },
          "level": 3,
          "productionInput": {
            "SERVANT": 1,
            "STONE": 1
          },
          "productionOutput": {
            "COIN": 2,
            "SHIELD": 2,
            "FAITH": 1
          },
          "color": "YELLOW",
          "victoryPoints": 10
        },
        {
          "cost": {
            "STONE": 7
          },
          "level": 3,
          "productionInput": {
            "SHIELD": 1
          },
          "productionOutput": {
            "SERVANT": 1,
            "FAITH": 3
          },
          "color": "YELLOW",
          "victoryPoints": 11
        },
        {
          "cost": {
            "SERVANT": 4,
            "STONE": 4
          },
          "level": 3,
          "productionInput": {
            "SHIELD": 1
          },
          "productionOutput": {
            "SERVANT": 3,
            "STONE": 1
          },
          "color": "YELLOW",
          "victoryPoints": 12
        }
      ]
    }
  ]
}